fastapi_another_jwt_auth/__init__.py
fastapi_another_jwt_auth/auth_config.py
fastapi_another_jwt_auth/auth_jwt.py
fastapi_another_jwt_auth/config.py
fastapi_another_jwt_auth/exceptions.py
fastapi_another_jwt_auth-0.1.11.dist-info/LICENSE
fastapi_another_jwt_auth-0.1.11.dist-info/METADATA
fastapi_another_jwt_auth-0.1.11.dist-info/WHEEL
fastapi_another_jwt_auth-0.1.11.dist-info/RECORD
