Metadata-Version: 2.1
Name: fastapi-another-jwt-auth
Version: 0.1.11
Summary: 
Home-page: https://github.com/GlitchCorp/fastapi-another-jwt-auth
License: MIT
Author: Mariusz Masztalerczuk
Author-email: mariusz@masztalerczuk.com
Requires-Python: >=3.8,<4.0
Classifier: Environment :: Web Environment
Classifier: Intended Audience :: Developers
Classifier: License :: OSI Approved :: MIT License
Classifier: Operating System :: OS Independent
Classifier: Programming Language :: Python :: 3
Classifier: Programming Language :: Python :: 3.8
Classifier: Programming Language :: Python :: 3.9
Classifier: Programming Language :: Python :: 3.10
Classifier: Programming Language :: Python :: 3.11
Classifier: Programming Language :: Python :: 3.12
Classifier: Topic :: Internet :: WWW/HTTP :: Dynamic Content
Classifier: Topic :: Software Development :: Libraries :: Python Modules
Requires-Dist: PyJWT (>=2.4.0,<3.0.0)
Requires-Dist: coverage (==6.4)
Requires-Dist: cryptography (>=41.0.3)
Requires-Dist: fastapi (>=0.65.3)
Requires-Dist: pydantic-settings (>=2.1.0,<3.0.0)
Project-URL: Repository, https://github.com/GlitchCorp/fastapi-another-jwt-auth
